liveplots/__init__.py
liveplots/filemonitor.py
liveplots/liveplot.py
liveplots/xmlrpcserver.py
liveplots/tests/__init__.py
liveplots/tests/test_filemonitor.py
liveplots/tests/test_xmlrpcserver.py
liveplots-0.9.0.dist-info/METADATA
liveplots-0.9.0.dist-info/WHEEL
liveplots-0.9.0.dist-info/top_level.txt
liveplots-0.9.0.dist-info/zip-safe
liveplots-0.9.0.dist-info/RECORD
