Metadata-Version: 2.1
Name: liveplots
Version: 0.9.0
Summary: Real-time live plot server
Home-page: https://github.com/fccoelho/liveplots
Author: Flávio Codeço Coelho
Author-email: fccoelho@gmail.com
License: GPL
Platform: UNKNOWN
Requires-Dist: numpy (>=1.2)
